graphdatascience/__init__.py
graphdatascience/call_builder.py
graphdatascience/call_parameters.py
graphdatascience/caller_base.py
graphdatascience/endpoints.py
graphdatascience/graph_data_science.py
graphdatascience/ignored_server_endpoints.py
graphdatascience/py.typed
graphdatascience/version.py
graphdatascience/algo/__init__.py
graphdatascience/algo/algo_endpoints.py
graphdatascience/algo/algo_proc_runner.py
graphdatascience/algo/single_mode_algo_endpoints.py
graphdatascience/error/__init__.py
graphdatascience/error/client_only_endpoint.py
graphdatascience/error/cypher_warning_handler.py
graphdatascience/error/endpoint_suggester.py
graphdatascience/error/gds_not_installed.py
graphdatascience/error/illegal_attr_checker.py
graphdatascience/error/unable_to_connect.py
graphdatascience/error/uncallable_namespace.py
graphdatascience/graph/__init__.py
graphdatascience/graph/base_graph_proc_runner.py
graphdatascience/graph/graph_alpha_proc_runner.py
graphdatascience/graph/graph_beta_proc_runner.py
graphdatascience/graph/graph_create_result.py
graphdatascience/graph/graph_cypher_runner.py
graphdatascience/graph/graph_endpoints.py
graphdatascience/graph/graph_entity_ops_runner.py
graphdatascience/graph/graph_export_runner.py
graphdatascience/graph/graph_object.py
graphdatascience/graph/graph_proc_runner.py
graphdatascience/graph/graph_project_runner.py
graphdatascience/graph/graph_remote_proc_runner.py
graphdatascience/graph/graph_remote_project_runner.py
graphdatascience/graph/graph_sample_runner.py
graphdatascience/graph/graph_type_check.py
graphdatascience/graph/nx_loader.py
graphdatascience/graph/ogb_loader.py
graphdatascience/model/__init__.py
graphdatascience/model/graphsage_model.py
graphdatascience/model/link_prediction_model.py
graphdatascience/model/model.py
graphdatascience/model/model_alpha_proc_runner.py
graphdatascience/model/model_beta_proc_runner.py
graphdatascience/model/model_endpoints.py
graphdatascience/model/model_proc_runner.py
graphdatascience-1.16.dist-info/licenses/LICENSE
graphdatascience-1.16.dist-info/METADATA
graphdatascience-1.16.dist-info/WHEEL
graphdatascience-1.16.dist-info/top_level.txt
graphdatascience-1.16.dist-info/RECORD
