Metadata-Version: 2.4
Name: graphdatascience
Version: 1.16
Summary: A Python client for the Neo4j Graph Data Science (GDS) library
Home-page: https://neo4j.com/product/graph-data-science/
Author: Neo4j
Author-email: team-gds@neo4j.org
License: Apache License 2.0
Project-URL: Documentation, https://neo4j.com/docs/graph-data-science-client/current/
Project-URL: Source, https://github.com/neo4j/graph-data-science-client
Project-URL: Bug Tracker, https://github.com/neo4j/graph-data-science-client/issues
Classifier: Development Status :: 5 - Production/Stable
Classifier: Intended Audience :: Developers
Classifier: Intended Audience :: Science/Research
Classifier: License :: OSI Approved :: Apache Software License
Classifier: Operating System :: OS Independent
Classifier: Programming Language :: Python :: 3
Classifier: Programming Language :: Python :: 3 :: Only
Classifier: Programming Language :: Python :: 3.9
Classifier: Programming Language :: Python :: 3.10
Classifier: Programming Language :: Python :: 3.11
Classifier: Programming Language :: Python :: 3.12
Classifier: Programming Language :: Python :: 3.13
Classifier: Topic :: Database
Classifier: Topic :: Scientific/Engineering
Classifier: Topic :: Software Development
Classifier: Typing :: Typed
Requires-Python: >=3.9
License-File: LICENSE
Requires-Dist: multimethod<3.0,>=1.0
Requires-Dist: neo4j<6.0,>=4.4.12
Requires-Dist: numpy<2.3
Requires-Dist: pandas<3.0,>=1.0
Requires-Dist: pyarrow<21.0,>=17.0
Requires-Dist: textdistance<5.0,>=4.0
Requires-Dist: tqdm<5.0,>=4.0
Requires-Dist: typing-extensions<5.0,>=4.0
Requires-Dist: requests
Requires-Dist: tenacity>=9.0
Provides-Extra: ogb
Requires-Dist: ogb<2.0,>=1.0; extra == "ogb"
Provides-Extra: networkx
Requires-Dist: networkx<4.0,>=2.0; extra == "networkx"
Provides-Extra: rust-ext
Requires-Dist: neo4j-rust-ext<6.0,>=4.4.12; extra == "rust-ext"
Dynamic: author
Dynamic: author-email
Dynamic: classifier
Dynamic: description
Dynamic: description-content-type
Dynamic: home-page
Dynamic: license
Dynamic: license-file
Dynamic: project-url
Dynamic: provides-extra
Dynamic: requires-dist
Dynamic: requires-python
Dynamic: summary
